Workbook
Name aporte: Sheet1!$D$17
Name patrimonio: Sheet1!$D$20
Name qtd_anos: Sheet1!$D$18
Name rendimento_carteira: Sheet1!$D$13
Name salario: Sheet1!$D$12
Name sugestao_investimento: Sheet1!$D$14
Name taxa_mensal: Sheet1!$D$19

Sheet Sheet1
B11: CONFIGURAÇÕES
B12: Salário | D12: 5000
B13: Rendimento Carteira | D13: 0.006
B14: Sugestão de Investimento | D14: =D12*30% -> 1500
B16: INVESTIMENTO MENSAL
B17: Quanto investir por mês? | D17: 1500
B18: Por quantos anos? | D18: 10
B19: Taxa de rendimento mensal | D19: 0.01079
B20: Patrimônio acumulado | D20: =FV(taxa_mensal,qtd_anos*12,aporte)*-1 -> 364926.32
B21: Dividendos mensais | D21: =patrimonio*rendimento_carteira -> 2189.5579
B23: CENÁRIOS | D23: DIVIDENDOS
A24: 2 | B24: Quanto em 2 anos? | C24: =FV($D$19,$A24*12,$D$17*-1) -> 40841.441 | D24: =C24*rendimento_carteira -> 245.04865
A25: 5 | B25: Quanto em 5 anos? | C25: =FV($D$19,$A25*12,$D$17*-1) -> 125665.37 | D25: =C25*rendimento_carteira -> 753.99223
A26: 10 | B26: Quanto em 10 anos? | C26: =FV($D$19,$A26*12,$D$17*-1) -> 364926.32 | D26: =C26*rendimento_carteira -> 2189.5579
A27: 20 | B27: Quanto em 20 anos? | C27: =FV($D$19,$A27*12,$D$17*-1) -> 1687797.6 | D27: =C27*rendimento_carteira -> 10126.786
A28: 30 | B28: Quanto em 30 anos? | C28: =FV($D$19,$A28*12,$D$17*-1) -> 6483254.5 | D28: =C28*rendimento_carteira -> 38899.527
B32: PERFIL | C32: Moderado
B33: VALOR A SER INVESTIDO POR MÊS | C33: =aporte -> 1500
B35: TIPO DE FII | C35: PERCENTUAL SUGERIDO | D35: VALORES
B36: PAPEL | C36: =VLOOKUP($C$32&"-"&B36,Planilha1!$B:$E,4,FALSE) -> 0.32 | D36: =C36*$C$33 -> 480
B37: TIJOLO | C37: =VLOOKUP($C$32&"-"&B37,Planilha1!$B:$E,4,FALSE) -> 0.35 | D37: =C37*$C$33 -> 525
B38: HIBRIDOS | C38: =VLOOKUP($C$32&"-"&B38,Planilha1!$B:$E,4,FALSE) -> 0.08 | D38: =C38*$C$33 -> 120
B39: FOFs | C39: =VLOOKUP($C$32&"-"&B39,Planilha1!$B:$E,4,FALSE) -> 0.05 | D39: =C39*$C$33 -> 75
B40: DESENVOLVIMENTO | C40: =VLOOKUP($C$32&"-"&B40,Planilha1!$B:$E,4,FALSE) -> 0.1 | D40: =C40*$C$33 -> 150
B41: HOTELARIAS | C41: =VLOOKUP($C$32&"-"&B41,Planilha1!$B:$E,4,FALSE) -> 0.1 | D41: =C41*$C$33 -> 150
D42: =SUM(D36:D41) -> 1500

Sheet Planilha1
B6: CHAVE | C6: PERFIL | D6: TIPO DE FII | E6: % | H6: %
B7: =C7&"-"&D7 -> Conservador-PAPEL | C7: Conservador | D7: PAPEL | E7: 0.3 | G7: Moderado-TIJOLO | H7: =VLOOKUP(B14,$B:$E,4,FALSE) -> 0.35
B8: =C8&"-"&D8 -> Conservador-TIJOLO | C8: Conservador | D8: TIJOLO | E8: 0.5
B9: =C9&"-"&D9 -> Conservador-HIBRIDOS | C9: Conservador | D9: HIBRIDOS | E9: 0.1
B10: =C10&"-"&D10 -> Conservador-FOFs | C10: Conservador | D10: FOFs | E10: 0.1
B11: =C11&"-"&D11 -> Conservador-DESENVOLVIMENTO | C11: Conservador | D11: DESENVOLVIMENTO | E11: 0
B12: =C12&"-"&D12 -> Conservador-HOTELARIAS | C12: Conservador | D12: HOTELARIAS | E12: 0
B13: =C13&"-"&D13 -> Moderado-PAPEL | C13: Moderado | D13: PAPEL | E13: 0.32
B14: =C14&"-"&D14 -> Moderado-TIJOLO | C14: Moderado | D14: TIJOLO | E14: 0.35
B15: =C15&"-"&D15 -> Moderado-HIBRIDOS | C15: Moderado | D15: HIBRIDOS | E15: 0.08
B16: =C16&"-"&D16 -> Moderado-FOFs | C16: Moderado | D16: FOFs | E16: 0.05
B17: =C17&"-"&D17 -> Moderado-DESENVOLVIMENTO | C17: Moderado | D17: DESENVOLVIMENTO | E17: 0.1
B18: =C18&"-"&D18 -> Moderado-HOTELARIAS | C18: Moderado | D18: HOTELARIAS | E18: 0.1
B19: =C19&"-"&D19 -> Agressivo-PAPEL | C19: Agressivo | D19: PAPEL | E19: 0.5
... B24: =C24&"-"&D24 -> Agressivo-HOTELARIAS | C24: Agressivo | D24: HOTELARIAS | E24: 0.1
